cubic/__init__.py
0x01_cubic_sdk-3.0.0.dist-info/LICENSE
0x01_cubic_sdk-3.0.0.dist-info/METADATA
0x01_cubic_sdk-3.0.0.dist-info/WHEEL
0x01_cubic_sdk-3.0.0.dist-info/top_level.txt
0x01_cubic_sdk-3.0.0.dist-info/RECORD
