Metadata-Version: 2.1
Name: 0x01-cubic-sdk
Version: 3.0.0
Summary: Cubic SDK
Home-page: https://github.com/Smart-Hypercube/cubic-sdk
Author: Hypercube
Author-email: hypercube@0x01.me
License: MIT
Platform: UNKNOWN
Classifier: Development Status :: 5 - Production/Stable
Classifier: Intended Audience :: Developers
Classifier: License :: OSI Approved :: MIT License
Classifier: Programming Language :: Python
Classifier: Programming Language :: Python :: 3 :: Only
Classifier: Programming Language :: Python :: 3.7
Requires-Python: >=3.7
Requires-Dist: msgpack (>=1.0)
Requires-Dist: requests (>=2.21)
